dnsmadeeasy/__init__.py
dnsmadeeasy/_info.py
dnsmadeeasy/api.py
dnsmadeeasy/driver.py
libcloud_dnsmadeeasy-1.0.dist-info/DESCRIPTION.rst
libcloud_dnsmadeeasy-1.0.dist-info/METADATA
libcloud_dnsmadeeasy-1.0.dist-info/RECORD
libcloud_dnsmadeeasy-1.0.dist-info/WHEEL
libcloud_dnsmadeeasy-1.0.dist-info/metadata.json
libcloud_dnsmadeeasy-1.0.dist-info/top_level.txt
libcloud_dnsmadeeasy-1.0.dist-info/zip-safe
