Metadata-Version: 2.0
Name: libcloud-dnsmadeeasy
Version: 1.0
Summary: A driver for DNSMadeEasy for libcloud DNS
Home-page: https://github.com/moses-palmer/libcloud-dnsmadeeasy
Author: Moses Palmér
Author-email: moses.palmer@gmail.com
License: UNKNOWN
Platform: UNKNOWN
Requires-Dist: apache-libcloud (>=0.14.1)
Requires-Dist: hammock (>=0.2.4)
